{
  "ANNUAL RAINFALL (Millimeters)": {
    "mean": 918.0778,
    "std": 539.1467,
    "min": 9.1,
    "max": 8409.0,
    "low": -160.2157,
    "high": 1996.3712
  },
  "KHARIF_RAIN_MM": {
    "mean": 709.2893,
    "std": 440.3386,
    "min": 0.0,
    "max": 5729.2,
    "low": -171.388,
    "high": 1589.9665
  },
  "RABI_RAIN_MM": {
    "mean": 133.739,
    "std": 169.6985,
    "min": 0.0,
    "max": 3887.4,
    "low": -205.6579,
    "high": 473.1359
  },
  "COTTON IRRIGATED AREA (1000 ha)": {
    "mean": 14.9063,
    "std": 48.3163,
    "min": 0.0,
    "max": 540.85,
    "low": -81.7263,
    "high": 111.5389
  },
  "CANALS AREA (1000 ha)": {
    "mean": 54.06,
    "std": 109.445,
    "min": 0.0,
    "max": 913.62,
    "low": -164.8301,
    "high": 272.95
  },
  "TUBE WELLS AREA (1000 ha)": {
    "mean": 40.459,
    "std": 82.0991,
    "min": 0.0,
    "max": 702.29,
    "low": -123.7392,
    "high": 204.6573
  },
  "TOTAL WELLS AREA (1000 ha)": {
    "mean": 85.8111,
    "std": 89.425,
    "min": 0.0,
    "max": 702.29,
    "low": -93.0388,
    "high": 264.6611
  },
  "NET AREA (1000 ha)": {
    "mean": 160.8707,
    "std": 147.7853,
    "min": 0.06,
    "max": 985.44,
    "low": -134.6998,
    "high": 456.4412
  },
  "GROSS AREA (1000 ha)": {
    "mean": 217.3429,
    "std": 236.7949,
    "min": 0.0,
    "max": 1869.64,
    "low": -256.2469,
    "high": 690.9327
  },
  "NET CROPPED AREA (1000 ha)": {
    "mean": 545.9077,
    "std": 282.4106,
    "min": -5.0,
    "max": 1642.04,
    "low": -18.9135,
    "high": 1110.7288
  },
  "GROSS CROPPED AREA (1000 ha)": {
    "mean": 671.0721,
    "std": 333.6823,
    "min": -5.0,
    "max": 2325.94,
    "low": 3.7075,
    "high": 1338.4367
  },
  "KHARIF_TMAX": {
    "mean": 32.4006,
    "std": 2.6219,
    "min": 22.1575,
    "max": 40.625,
    "low": 27.1567,
    "high": 37.6445
  },
  "KHARIF_TMIN": {
    "mean": 24.0668,
    "std": 1.9575,
    "min": 14.215,
    "max": 28.5225,
    "low": 20.1518,
    "high": 27.9817
  },
  "RABI_TMAX": {
    "mean": 28.7566,
    "std": 2.5963,
    "min": 11.162,
    "max": 33.614,
    "low": 23.564,
    "high": 33.9493
  },
  "RABI_TMIN": {
    "mean": 15.0347,
    "std": 3.4636,
    "min": 2.038,
    "max": 24.332,
    "low": 8.1075,
    "high": 21.9619
  },
  "ANNUAL_TMAX": {
    "mean": 31.8651,
    "std": 1.939,
    "min": 16.7283,
    "max": 35.9117,
    "low": 27.9871,
    "high": 35.7431
  },
  "ANNUAL_TMIN": {
    "mean": 19.8462,
    "std": 2.0302,
    "min": 7.7783,
    "max": 25.9983,
    "low": 15.7858,
    "high": 23.9066
  },
  "DIURNAL_TEMP_RANGE": {
    "mean": 12.0177,
    "std": 1.73,
    "min": 6.66,
    "max": 16.2275,
    "low": 8.5576,
    "high": 15.4778
  },
  "N_KG_PER_HA": {
    "mean": 53.6902,
    "std": 42.4613,
    "min": 0.1,
    "max": 287.61,
    "low": -31.2324,
    "high": 138.6128
  },
  "P_KG_PER_HA": {
    "mean": 21.4024,
    "std": 14.9961,
    "min": 0.04,
    "max": 104.05,
    "low": -8.5899,
    "high": 51.3947
  },
  "K_KG_PER_HA": {
    "mean": 9.3991,
    "std": 14.3934,
    "min": 0.0,
    "max": 165.36,
    "low": -19.3877,
    "high": 38.1859
  },
  "NPK_TOTAL_KG_PER_HA": {
    "mean": 84.6498,
    "std": 63.7133,
    "min": 0.09,
    "max": 478.66,
    "low": -42.7767,
    "high": 212.0763
  },
  "FERT_KHARIF_TONS": {
    "mean": 6448.2923,
    "std": 6141.1372,
    "min": 0.0,
    "max": 37795.0,
    "low": -5833.9821,
    "high": 18730.5667
  },
  "FERT_RABI_TONS": {
    "mean": 24409.3617,
    "std": 21750.0793,
    "min": 0.0,
    "max": 145359.0,
    "low": -19090.7968,
    "high": 67909.5203
  },
  "GROWING_PERIOD_DAYS": {
    "mean": 168.0187,
    "std": 40.3856,
    "min": 28.0,
    "max": 300.0,
    "low": 87.2475,
    "high": 248.7899
  },
  "ANNUAL NORMAL RAINFALL (Millimeters)": {
    "mean": 984.3102,
    "std": 491.724,
    "min": 218.0,
    "max": 3667.0,
    "low": 0.8622,
    "high": 1967.7583
  },
  "COTTON_STATE_PRICE": {
    "mean": 789.2707,
    "std": 699.3859,
    "min": 94.4,
    "max": 4554.0,
    "low": -609.5011,
    "high": 2188.0425
  },
  "FERT_DATA_AVAILABLE": {
    "mean": 0.3937,
    "std": 0.4886,
    "min": 0.0,
    "max": 1.0,
    "low": -0.5835,
    "high": 1.3709
  },
  "RAINFALL_DEV_MM": {
    "mean": -66.2325,
    "std": 402.5046,
    "min": -2940.4,
    "max": 5387.0,
    "low": -871.2418,
    "high": 738.7768
  },
  "RAINFALL_DEV_PCT": {
    "mean": -4.3464,
    "std": 39.0413,
    "min": -98.592,
    "max": 365.2219,
    "low": -82.429,
    "high": 73.7363
  },
  "IRRIGATION_RATIO": {
    "mean": 0.372,
    "std": 0.4093,
    "min": 0.0,
    "max": 1.5,
    "low": -0.4465,
    "high": 1.1905
  },
  "CANAL_WELL_RATIO": {
    "mean": 0.305,
    "std": 0.3214,
    "min": 0.0,
    "max": 1.0,
    "low": -0.3377,
    "high": 0.9477
  },
  "WATER_INTENSITY": {
    "mean": 184.7527,
    "std": 726.1358,
    "min": 0.0,
    "max": 6378.0,
    "low": -1267.5189,
    "high": 1637.0242
  },
  "CROPPING_INTENSITY": {
    "mean": 126.5558,
    "std": 22.3629,
    "min": 96.55,
    "max": 252.76,
    "low": 81.8299,
    "high": 171.2816
  },
  "NET_CROP_RATIO": {
    "mean": 0.8119,
    "std": 0.1273,
    "min": 0.0,
    "max": 1.0,
    "low": 0.5573,
    "high": 1.0664
  },
  "HEAT_STRESS": {
    "mean": 0.7396,
    "std": 1.2159,
    "min": 0.0,
    "max": 7.625,
    "low": -1.6922,
    "high": 3.1714
  },
  "COLD_STRESS": {
    "mean": 0.0025,
    "std": 0.0705,
    "min": 0.0,
    "max": 2.962,
    "low": -0.1385,
    "high": 0.1434
  },
  "KHARIF_TEMP_RANGE": {
    "mean": 8.3338,
    "std": 1.3249,
    "min": 4.2125,
    "max": 12.8525,
    "low": 5.6841,
    "high": 10.9836
  },
  "RABI_TEMP_RANGE": {
    "mean": 13.7219,
    "std": 2.4427,
    "min": 5.79,
    "max": 18.192,
    "low": 8.8366,
    "high": 18.6073
  },
  "N_SHARE": {
    "mean": 0.6309,
    "std": 0.1088,
    "min": 0.3417,
    "max": 1.0,
    "low": 0.4134,
    "high": 0.8485
  },
  "FERT_IRR_INTERACTION": {
    "mean": 36.1129,
    "std": 54.0484,
    "min": 0.0,
    "max": 274.9306,
    "low": -71.9839,
    "high": 144.2098
  },
  "YIELD_LAG_1": {
    "mean": 214.2326,
    "std": 155.2271,
    "min": 13.67,
    "max": 3000.0,
    "low": -96.2215,
    "high": 524.6868
  },
  "YIELD_LAG_3": {
    "mean": 208.5052,
    "std": 148.3577,
    "min": 13.67,
    "max": 3000.0,
    "low": -88.2102,
    "high": 505.2206
  },
  "YEAR_TREND": {
    "mean": 19.501,
    "std": 11.4369,
    "min": 0.0,
    "max": 39.0,
    "low": -3.3727,
    "high": 42.3747
  },
  "DECADE": {
    "mean": 1981.0083,
    "std": 12.0864,
    "min": 1960.0,
    "max": 2000.0,
    "low": 1956.8354,
    "high": 2005.1811
  },
  "PRICE_TREND_3YR": {
    "mean": 816.4487,
    "std": 682.722,
    "min": 110.0,
    "max": 4284.6667,
    "low": -548.9953,
    "high": 2181.8928
  },
  "SOIL_INCEPTISOLS": {
    "mean": 0.1704,
    "std": 0.376,
    "min": 0.0,
    "max": 1.0,
    "low": -0.5816,
    "high": 0.9225
  },
  "SOIL_LOAMY": {
    "mean": 0.025,
    "std": 0.156,
    "min": 0.0,
    "max": 1.0,
    "low": -0.2871,
    "high": 0.337
  },
  "SOIL_ORTHIDS": {
    "mean": 0.1079,
    "std": 0.3103,
    "min": 0.0,
    "max": 1.0,
    "low": -0.5127,
    "high": 0.7286
  },
  "SOIL_OTHER": {
    "mean": 0.0236,
    "std": 0.1519,
    "min": 0.0,
    "max": 1.0,
    "low": -0.2802,
    "high": 0.3275
  },
  "SOIL_PSSAMENTS": {
    "mean": 0.0691,
    "std": 0.2536,
    "min": 0.0,
    "max": 1.0,
    "low": -0.4382,
    "high": 0.5764
  },
  "SOIL_SANDY": {
    "mean": 0.122,
    "std": 0.3273,
    "min": 0.0,
    "max": 1.0,
    "low": -0.5326,
    "high": 0.7766
  },
  "SOIL_UDALFS": {
    "mean": 0.0122,
    "std": 0.1099,
    "min": 0.0,
    "max": 1.0,
    "low": -0.2076,
    "high": 0.2321
  },
  "SOIL_UDOLLS/UDALFS": {
    "mean": 0.0066,
    "std": 0.081,
    "min": 0.0,
    "max": 1.0,
    "low": -0.1555,
    "high": 0.1687
  },
  "SOIL_UDUPTS/UDALFS": {
    "mean": 0.0066,
    "std": 0.081,
    "min": 0.0,
    "max": 1.0,
    "low": -0.1555,
    "high": 0.1687
  },
  "SOIL_USTALF/USTOLLS": {
    "mean": 0.0585,
    "std": 0.2347,
    "min": 0.0,
    "max": 1.0,
    "low": -0.4109,
    "high": 0.528
  },
  "SOIL_USTALFS-OCHREPTS": {
    "mean": 0.0286,
    "std": 0.1667,
    "min": 0.0,
    "max": 1.0,
    "low": -0.3048,
    "high": 0.362
  },
  "SOIL_VERTIC": {
    "mean": 0.3273,
    "std": 0.4693,
    "min": 0.0,
    "max": 1.0,
    "low": -0.6112,
    "high": 1.2658
  },
  "SOIL_VERTISOLS": {
    "mean": 0.0421,
    "std": 0.2009,
    "min": 0.0,
    "max": 1.0,
    "low": -0.3597,
    "high": 0.444
  }
}